montague_toml/__init__.py
montague_toml/toml.py
montague_toml-0.2.0.dist-info/DESCRIPTION.rst
montague_toml-0.2.0.dist-info/entry_points.txt
montague_toml-0.2.0.dist-info/METADATA
montague_toml-0.2.0.dist-info/metadata.json
montague_toml-0.2.0.dist-info/RECORD
montague_toml-0.2.0.dist-info/top_level.txt
montague_toml-0.2.0.dist-info/WHEEL
