Metadata-Version: 2.0
Name: montague-toml
Version: 0.2.0
Summary: Montague provides functions to load WSGI apps and servers based on configuration files. montague_toml loads configuration from TOML markup files.
Home-page: https://github.com/inklesspen/montague_toml
Author: Jon Rosebaugh
Author-email: jon@inklesspen.com
License: BSD
Platform: UNKNOWN
Classifier: Development Status :: 3 - Alpha
Classifier: Intended Audience :: Developers
Classifier: License :: OSI Approved :: MIT License
Classifier: Operating System :: Unix
Classifier: Operating System :: POSIX
Classifier: Operating System :: Microsoft :: Windows
Classifier: Programming Language :: Python
Classifier: Programming Language :: Python :: 2.6
Classifier: Programming Language :: Python :: 2.7
Classifier: Programming Language :: Python :: 3
Classifier: Programming Language :: Python :: 3.3
Classifier: Programming Language :: Python :: 3.4
Classifier: Programming Language :: Python :: Implementation :: CPython
Classifier: Programming Language :: Python :: Implementation :: PyPy
Classifier: Topic :: Internet :: WWW/HTTP :: WSGI
Classifier: Topic :: Utilities
Requires-Dist: montague (>=0.2.0)
Requires-Dist: pytoml (>=0.1.2)
